Dockerfile_Compile
Dockerfile_Deploy
README.md
deploy_build.sh
setup.py
test_compile.py
test_sdk.py
test_server.py
muggle/__init__.py
muggle/categories.py
muggle/config.py
muggle/constants.py
muggle/entity.py
muggle/exception.py
muggle/fastapi_app.py
muggle/handler.py
muggle/logger.py
muggle/main.py
muggle/requirements.txt
muggle/sdk.py
muggle/setup_env.py
muggle/utils.py
muggle/corpus/builtin.dict
muggle/engine/__init__.py
muggle/engine/base.py
muggle/engine/model.py
muggle/engine/project.py
muggle/engine/session.py
muggle/engine/utils.py
muggle/engine/components/__init__.py
muggle/engine/components/preprocess.py
muggle/engine/impl/__init__.py
muggle/logic/__init__.py
muggle/logic/base.py
muggle/logic/click.py
muggle/logic/cls.py
muggle/logic/ctc.py
muggle/logic/jigsaw.py
muggle/logic/reg.py
muggle/logic/utils.py
muggle/middleware/__init__.py
muggle/middleware/charge.py
muggle/middleware/docs.py
muggle/middleware/draw.py
muggle/middleware/md5_cache.py
muggle/middleware/memory_load.py
muggle/middleware/verification.py
muggle/package/__init__.py
muggle/package/config.py
muggle/package/data-hiding.py
muggle/package/hinted-mods.py
muggle/package/obfuscate.py
muggle/package/prepare.py
muggle/package/runner.py
muggle/package/lib/CentOS7-Base-163.repo
muggle/package/lib/Python-3.9.9.tar.gz
muggle/package/lib/appimagetool-x86_64.AppImage
muggle/package/lib/gunicorn-master.zip
muggle/package/lib/patchelf-0.14.3-x86_64.tar.gz
muggle/package/lib/zlibwapi.dll
muggle/package/lib/cv/__init__.py
muggle/package/lib/cv/cv2.cpython-39-x86_64-linux-gnu.so
muggle/package/lib/cv/lib.tar.gz
muggle/pages/__init__.py
muggle/pages/base.py
muggle/pages/docs.py
muggle/pages/guide.py
muggle/pages/preview.py
muggle/pages/utils.py
muggle/pages/components/__init__.py
muggle/pages/components/base.py
muggle/pages/components/displays.py
muggle/pages/components/examples.py
muggle/pages/components/inputs.py
muggle/pages/demo/__init__.py
muggle/pages/demo/http.py
muggle/resource/icon.ico
muggle_deploy.egg-info/PKG-INFO
muggle_deploy.egg-info/SOURCES.txt
muggle_deploy.egg-info/dependency_links.txt
muggle_deploy.egg-info/requires.txt
muggle_deploy.egg-info/top_level.txt
