Metadata-Version: 2.1
Name: muggle-deploy
Version: 1.0.0
Summary: muggle-deploy
Home-page: https://github.com/kerlomz
Author: kerlomz
License: UNKNOWN
Platform: UNKNOWN
Classifier: Programming Language :: Python :: 3
Classifier: License :: OSI Approved :: MIT License
Classifier: Operating System :: OS Independent
Requires-Python: >=3.9,<3.11
Provides-Extra: gpu
